hive/__init__.py
hive/api.py
hive/decorators.py
hive/exceptions.py
hive/infrastrucure_keys.py
hive/tools.py
hive/version.py
hive/cookbook/__init__.py
hive/cookbook/acl_docs.py
hive/cookbook/acl_overrides.py
hive/cookbook/analytics.py
hive/cookbook/anomalies.py
hive/cookbook/apple.py
hive/cookbook/automata_ingest.py
hive/cookbook/calendars.py
hive/cookbook/contacts.py
hive/cookbook/cost_tagging.py
hive/cookbook/cost_tags.py
hive/cookbook/cost_tree_nodes.py
hive/cookbook/cost_tree_resources.py
hive/cookbook/cost_views.py
hive/cookbook/customers.py
hive/cookbook/dashboards.py
hive/cookbook/dispatchers.py
hive/cookbook/downtimes.py
hive/cookbook/external_tickets.py
hive/cookbook/features.py
hive/cookbook/files.py
hive/cookbook/firmware_updates.py
hive/cookbook/google.py
hive/cookbook/groups.py
hive/cookbook/jobs.py
hive/cookbook/last_object_status.py
hive/cookbook/last_status.py
hive/cookbook/login.py
hive/cookbook/messages.py
hive/cookbook/metric_ingest.py
hive/cookbook/metric_types.py
hive/cookbook/metrics.py
hive/cookbook/microsoft.py
hive/cookbook/notification_provider_types.py
hive/cookbook/notification_providers.py
hive/cookbook/objects.py
hive/cookbook/opening_reasons.py
hive/cookbook/probe_types.py
hive/cookbook/probes.py
hive/cookbook/probes_log_ingest.py
hive/cookbook/profile_topics.py
hive/cookbook/qr_code.py
hive/cookbook/questions.py
hive/cookbook/reason_for_closure.py
hive/cookbook/retention_rules.py
hive/cookbook/schedules.py
hive/cookbook/services.py
hive/cookbook/sites.py
hive/cookbook/terms_and_conditions.py
hive/cookbook/tests.py
hive/cookbook/tree_hierarchy.py
hive/cookbook/tree_hierarchy_v2.py
hive/cookbook/ts_automata_state.py
hive/cookbook/ts_cost_azure_raw.py
hive/cookbook/ts_cost_management.py
hive/cookbook/ts_cost_management_v2.py
hive/cookbook/ts_metric_status.py
hive/cookbook/ts_metric_value.py
hive/cookbook/ts_ntop_flows.py
hive/cookbook/ts_service_status.py
hive/cookbook/ts_service_value.py
hive/cookbook/users.py
xautomata_hive-4.0.33.dist-info/licenses/LICENSE
xautomata_hive-4.0.33.dist-info/METADATA
xautomata_hive-4.0.33.dist-info/WHEEL
xautomata_hive-4.0.33.dist-info/top_level.txt
xautomata_hive-4.0.33.dist-info/RECORD
