Metadata-Version: 2.4
Name: xautomata-hive
Version: 4.0.33
Home-page: https://github.com/sherlogic/xautomata-hive.git
Author: Enrico Ferro - Andrea Jacassi
Author-email: 
License: MIT
Requires-Python: >=3.8.0
License-File: LICENSE
Requires-Dist: requests==2.32.5
Requires-Dist: tqdm==4.67.1
Requires-Dist: urllib3==2.5.0
Dynamic: author
Dynamic: description
Dynamic: description-content-type
Dynamic: home-page
Dynamic: license
Dynamic: license-file
Dynamic: requires-dist
Dynamic: requires-python
